LICENSE
MANIFEST.in
README.md
setup.py
libpythonproGG/__init__.py
libpythonproGG/github_api.py
libpythonproGG.egg-info/PKG-INFO
libpythonproGG.egg-info/SOURCES.txt
libpythonproGG.egg-info/dependency_links.txt
libpythonproGG.egg-info/not-zip-safe
libpythonproGG.egg-info/requires.txt
libpythonproGG.egg-info/top_level.txt